microscoper/__init__.py
microscoper/__main__.py
microscoper/args.py
microscoper/io.py
microscoper-0.3.1.dist-info/DESCRIPTION.rst
microscoper-0.3.1.dist-info/METADATA
microscoper-0.3.1.dist-info/RECORD
microscoper-0.3.1.dist-info/WHEEL
microscoper-0.3.1.dist-info/entry_points.txt
microscoper-0.3.1.dist-info/metadata.json
microscoper-0.3.1.dist-info/top_level.txt
